skeval/__init__.py
skeval/py.typed
scikit_eval-0.1.0.dist-info/WHEEL
scikit_eval-0.1.0.dist-info/METADATA
scikit_eval-0.1.0.dist-info/RECORD
